{
  "@class":"model.gamelogic.GameState$Game",
  "boardHashesMap":null,
  "description":"Your game description here...",
  "layout":"BELGIAN_DAISY",
  "moves":[
    "a1b2",
    "i5h5",
    "a2b3",
    "i6h6",
    "b1c2",
    "g4g5",
    "c2d3",
    "g5g6",
    "e4d4",
    "b6c6",
    "b2b3",
    "g7g8",
    "b3b4",
    "d6c6",
    "b4b5",
    "a4b4",
    "d4c4",
    "a4a3",
    "b6b5",
    "h4h6i7",
    "i9h8",
    "i5i7h4",
    "d3c3",
    "g8g9f7",
    "a3b4",
    "f8g8",
    "c5b5",
    "g8f7",
    "a5b5",
    "c6d6",
    "b5c5",
    "f7f6",
    "b3c4",
    "h4h5g5",
    "b4c4",
    "g4f4",
    "h7g7",
    "e4e5",
    "i8h8",
    "g5f5",
    "b5b4",
    "f4f5",
    "g8g7",
    "h6g5",
    "h9h8",
    "f5f6",
    "f9e9",
    "f4g5e4",
    "e9e8",
    "d6d5",
    "e6d6",
    "e7e6",
    "h7g7",
    "d4d5",
    "b4c4",
    "e6e7",
    "e9f9",
    "d5d6",
    "d8e9",
    "d7e8",
    "g7f7",
    "d7d6",
    "h8g7",
    "f9e8",
    "g7f7",
    "c7b6",
    "d7c6",
    "b6b5",
    "c4d4",
    "f6e6",
    "c6c5",
    "f4f5",
    "g6g5",
    "d5e6",
    "g5f4",
    "f5e5",
    "c5c4",
    "e8d7",
    "c2d2",
    "f8f7",
    "e9e8",
    "e6e5",
    "e8e7",
    "b5c5",
    "c4c3",
    "c5d6",
    "f4f3",
    "d7e7",
    "c2b2",
    "f5e4",
    "f3e2",
    "d6e7",
    "g8g9h8",
    "f8f7",
    "h9h8",
    "d3e4",
    "e3d3",
    "e7f7",
    "i7h6",
    "e5f6",
    "b2c3",
    "g6f5",
    "e6e5",
    "f6g7",
    "c3d4",
    "g7g6",
    "b1c1",
    "i9h9",
    "c1d2",
    "h8h9g7",
    "h6g5",
    "g8f7",
    "d4e4",
    "g4h5",
    "e2f3",
    "h5h6",
    "f3e3",
    "c3d4",
    "f4e4",
    "c4c5",
    "e3e4",
    "h6h7",
    "g5f4",
    "g7g6",
    "d2d3",
    "h8g8",
    "f4e4",
    "f7g8h8",
    "c2c3",
    "h7g6",
    "e6e5",
    "h8h7",
    "c4d5",
    "e3f4",
    "f6f7",
    "g7f6",
    "d4e5",
    "f4g5",
    "f7f6",
    "e7f7",
    "d3e4",
    "h7g7",
    "c3c2d4",
    "i8h7",
    "d3d4",
    "h6g5",
    "d4e4",
    "h7h6",
    "d6d5",
    "d7d6",
    "g6f6",
    "h6g6",
    "d6e6",
    "c6c5",
    "f4f5",
    "g4f4",
    "f7e6",
    "f8e7",
    "d5e5",
    "h6h7",
    "g5f5",
    "h7g7",
    "c4d4",
    "b3c4",
    "f4f5",
    "g4h5f4",
    "f7f6",
    "f8f7",
    "f4f5",
    "f3e3",
    "g6f5",
    "c5c4",
    "f6e5",
    "b2c2",
    "f5e4",
    "b1b2",
    "d5d4",
    "d1e2",
    "e6e5",
    "d6e7d5",
    "e5e4"
  ],
  "players":[
    "player",
    "same player"
  ]
}