{
  "@class":"model.gamelogic.GameState$Game",
  "boardHashesMap":null,
  "description":"Your game description here...",
  "layout":"BELGIAN_DAISY",
  "moves":[
    "i9h8",
    "a5b5",
    "i8h7",
    "a4b4",
    "h9g8",
    "c6c5",
    "g8f7",
    "c5c4",
    "e6f6",
    "h4g4",
    "f6g6",
    "c3c2",
    "h8h7",
    "h4g4",
    "f7g7",
    "c2c1d3",
    "i7i6",
    "d2d3",
    "i5h5",
    "b6b5c5",
    "g7g6",
    "g3f3",
    "a1b2",
    "c6c5",
    "b1a1",
    "d3c3",
    "i6h5",
    "c5b4",
    "h5g4",
    "d1d2",
    "e2f3",
    "b4b3",
    "h6g5",
    "d5c4",
    "h7h6",
    "b3b2",
    "h6g5",
    "c3b2"
  ],
  "players":[
    "player",
    "same player"
  ]
}